[{"code":"430702","name":"武陵区","childs":[{"code":"430702001","name":"启明街道"},{"code":"430702002","name":"府坪街道"},{"code":"430702003","name":"穿紫河街道"},{"code":"430702004","name":"丹阳街道"},{"code":"430702005","name":"白马湖街道"},{"code":"430702006","name":"德山街道"},{"code":"430702007","name":"东江街道"},{"code":"430702008","name":"永安街道"},{"code":"430702009","name":"南坪街道"},{"code":"430702010","name":"长庚街道"},{"code":"430702011","name":"芷兰街道"},{"code":"430702012","name":"芙蓉街道"},{"code":"430702013","name":"柳叶湖街道"},{"code":"430702014","name":"七里桥街道"},{"code":"430702015","name":"樟木桥街道"},{"code":"430702100","name":"河洑镇"},{"code":"430702102","name":"白鹤镇"},{"code":"430702200","name":"芦荻山乡"},{"code":"430702204","name":"丹洲乡"}]},{"code":"430703","name":"鼎城区","childs":[{"code":"430703001","name":"玉霞街道"},{"code":"430703002","name":"红云街道"},{"code":"430703003","name":"郭家铺街道"},{"code":"430703004","name":"斗姆湖街道"},{"code":"430703101","name":"蒿子港镇"},{"code":"430703102","name":"中河口镇"},{"code":"430703103","name":"十美堂镇"},{"code":"430703104","name":"牛鼻滩镇"},{"code":"430703105","name":"韩公渡镇"},{"code":"430703106","name":"石公桥镇"},{"code":"430703107","name":"镇德桥镇"},{"code":"430703108","name":"周家店镇"},{"code":"430703110","name":"双桥坪镇"},{"code":"430703111","name":"灌溪镇"},{"code":"430703112","name":"蔡家岗镇"},{"code":"430703114","name":"草坪镇"},{"code":"430703115","name":"石门桥镇"},{"code":"430703116","name":"谢家铺镇"},{"code":"430703117","name":"黄土店镇"},{"code":"430703118","name":"尧天坪镇"},{"code":"430703121","name":"石板滩镇"},{"code":"430703122","name":"花岩溪镇"},{"code":"430703204","name":"许家桥回族维吾尔族乡"},{"code":"430703500","name":"鼎城区园艺场"},{"code":"430703501","name":"特种养殖场"},{"code":"430703502","name":"花岩溪林场"},{"code":"430703503","name":"贺家山原种场"}]},{"code":"430721","name":"安乡县","childs":[{"code":"430721100","name":"深柳镇"},{"code":"430721101","name":"大鲸港镇"},{"code":"430721102","name":"黄山头镇"},{"code":"430721103","name":"三岔河镇"},{"code":"430721104","name":"官垱镇"},{"code":"430721105","name":"下渔口镇"},{"code":"430721106","name":"陈家嘴镇"},{"code":"430721108","name":"大湖口镇"},{"code":"430721201","name":"安障乡"},{"code":"430721205","name":"安全乡"},{"code":"430721208","name":"安丰乡"},{"code":"430721210","name":"安康乡"}]},{"code":"430722","name":"汉寿县","childs":[{"code":"430722001","name":"龙阳街道"},{"code":"430722002","name":"辰阳街道"},{"code":"430722003","name":"沧浪街道"},{"code":"430722004","name":"株木山街道"},{"code":"430722101","name":"蒋家嘴镇"},{"code":"430722102","name":"岩汪湖镇"},{"code":"430722103","name":"坡头镇"},{"code":"430722104","name":"酉港镇"},{"code":"430722105","name":"洲口镇"},{"code":"430722106","name":"罐头嘴镇"},{"code":"430722107","name":"沧港镇"},{"code":"430722108","name":"朱家铺镇"},{"code":"430722109","name":"太子庙镇"},{"code":"430722111","name":"崔家桥镇"},{"code":"430722112","name":"军山铺镇"},{"code":"430722113","name":"百禄桥镇"},{"code":"430722114","name":"西湖镇"},{"code":"430722115","name":"洋淘湖镇"},{"code":"430722117","name":"丰家铺镇"},{"code":"430722118","name":"龙潭桥镇"},{"code":"430722205","name":"聂家桥乡"},{"code":"430722206","name":"毛家滩回族维吾尔族乡"},{"code":"430722501","name":"西湖管理区"}]},{"code":"430723","name":"澧县","childs":[{"code":"430723001","name":"澧西街道"},{"code":"430723002","name":"澧阳街道"},{"code":"430723003","name":"澧浦街道"},{"code":"430723004","name":"澧澹街道"},{"code":"430723102","name":"小渡口镇"},{"code":"430723103","name":"梦溪镇"},{"code":"430723104","name":"复兴镇"},{"code":"430723105","name":"盐井镇"},{"code":"430723107","name":"大堰垱镇"},{"code":"430723108","name":"王家厂镇"},{"code":"430723109","name":"金罗镇"},{"code":"430723110","name":"码头铺镇"},{"code":"430723112","name":"甘溪滩镇"},{"code":"430723113","name":"火连坡镇"},{"code":"430723114","name":"澧南镇"},{"code":"430723115","name":"如东镇"},{"code":"430723116","name":"涔南镇"},{"code":"430723117","name":"官垸镇"},{"code":"430723118","name":"城头山镇"}]},{"code":"430724","name":"临澧县","childs":[{"code":"430724100","name":"安福镇"},{"code":"430724101","name":"合口镇"},{"code":"430724102","name":"新安镇"},{"code":"430724103","name":"佘市桥镇"},{"code":"430724104","name":"太浮镇"},{"code":"430724105","name":"四新岗镇"},{"code":"430724106","name":"停弦渡镇"},{"code":"430724107","name":"修梅镇"},{"code":"430724204","name":"烽火乡"},{"code":"430724209","name":"刻木山乡"}]},{"code":"430725","name":"桃源县","childs":[{"code":"430725100","name":"漳江镇"},{"code":"430725101","name":"陬市镇"},{"code":"430725102","name":"盘塘镇"},{"code":"430725103","name":"热市镇"},{"code":"430725104","name":"黄石镇"},{"code":"430725105","name":"漆河镇"},{"code":"430725106","name":"理公港镇"},{"code":"430725107","name":"观音寺镇"},{"code":"430725108","name":"龙潭镇"},{"code":"430725109","name":"三阳港镇"},{"code":"430725110","name":"剪市镇"},{"code":"430725111","name":"茶庵铺镇"},{"code":"430725112","name":"西安镇"},{"code":"430725113","name":"沙坪镇"},{"code":"430725114","name":"桃花源镇"},{"code":"430725115","name":"架桥镇"},{"code":"430725116","name":"马鬃岭镇"},{"code":"430725117","name":"夷望溪镇"},{"code":"430725200","name":"青林回族维吾尔族乡"},{"code":"430725202","name":"枫树维吾尔族回族乡"},{"code":"430725203","name":"木塘垸乡"},{"code":"430725206","name":"双溪口乡"},{"code":"430725208","name":"九溪乡"},{"code":"430725211","name":"牛车河乡"},{"code":"430725212","name":"佘家坪乡"},{"code":"430725216","name":"泥窝潭乡"},{"code":"430725221","name":"杨溪桥乡"},{"code":"430725223","name":"郑家驿乡"}]},{"code":"430726","name":"石门县","childs":[{"code":"430726001","name":"楚江街道"},{"code":"430726002","name":"永兴街道"},{"code":"430726003","name":"宝峰街道"},{"code":"430726004","name":"二都街道"},{"code":"430726101","name":"蒙泉镇"},{"code":"430726102","name":"夹山镇"},{"code":"430726103","name":"易家渡镇"},{"code":"430726104","name":"新关镇"},{"code":"430726105","name":"皂市镇"},{"code":"430726106","name":"维新镇"},{"code":"430726107","name":"太平镇"},{"code":"430726108","name":"磨市镇"},{"code":"430726109","name":"壶瓶山镇"},{"code":"430726110","name":"南北镇"},{"code":"430726111","name":"白云镇"},{"code":"430726201","name":"新铺乡"},{"code":"430726203","name":"三圣乡"},{"code":"430726204","name":"子良乡"},{"code":"430726205","name":"所街乡"},{"code":"430726206","name":"雁池乡"},{"code":"430726207","name":"罗坪乡"},{"code":"430726500","name":"秀坪园艺场"},{"code":"430726502","name":"东山峰农场"},{"code":"430726503","name":"大同山林场"},{"code":"430726504","name":"白云山林场"},{"code":"430726505","name":"洛浦寺林场"},{"code":"430726506","name":"夹山管理处"}]},{"code":"430781","name":"津市市","childs":[{"code":"430781001","name":"三洲驿街道"},{"code":"430781002","name":"汪家桥街道"},{"code":"430781003","name":"襄阳街街道"},{"code":"430781004","name":"金鱼岭街道"},{"code":"430781005","name":"嘉山街道"},{"code":"430781100","name":"新洲镇"},{"code":"430781103","name":"白衣镇"},{"code":"430781105","name":"药山镇"},{"code":"430781106","name":"毛里湖镇"},{"code":"430781500","name":"涔澹农场"}]}]