[{"code":"610302","name":"渭滨区","childs":[{"code":"610302001","name":"金陵街道"},{"code":"610302002","name":"经二路街道"},{"code":"610302003","name":"清姜街道"},{"code":"610302004","name":"姜谭街道"},{"code":"610302005","name":"桥南街道"},{"code":"610302100","name":"马营镇"},{"code":"610302101","name":"石鼓镇"},{"code":"610302102","name":"神农镇"},{"code":"610302103","name":"高家镇"},{"code":"610302104","name":"八鱼镇"}]},{"code":"610303","name":"金台区","childs":[{"code":"610303001","name":"中山东路街道"},{"code":"610303002","name":"西关街道"},{"code":"610303003","name":"中山西路街道"},{"code":"610303004","name":"群众路街道"},{"code":"610303006","name":"东风路街道"},{"code":"610303007","name":"十里铺街道"},{"code":"610303008","name":"卧龙寺街道"},{"code":"610303100","name":"陈仓镇"},{"code":"610303101","name":"蟠龙镇"},{"code":"610303102","name":"金河镇"},{"code":"610303103","name":"硖石镇"}]},{"code":"610304","name":"陈仓区","childs":[{"code":"610304001","name":"虢镇街道"},{"code":"610304002","name":"东关街道"},{"code":"610304003","name":"千渭街道"},{"code":"610304101","name":"阳平镇"},{"code":"610304102","name":"千河镇"},{"code":"610304103","name":"磻溪镇"},{"code":"610304104","name":"天王镇"},{"code":"610304105","name":"慕仪镇"},{"code":"610304106","name":"周原镇"},{"code":"610304107","name":"贾村镇"},{"code":"610304109","name":"县功镇"},{"code":"610304110","name":"新街镇"},{"code":"610304111","name":"坪头镇"},{"code":"610304112","name":"香泉镇"},{"code":"610304113","name":"赤沙镇"},{"code":"610304114","name":"拓石镇"},{"code":"610304115","name":"凤阁岭镇"},{"code":"610304116","name":"钓渭镇"}]},{"code":"610322","name":"凤翔县","childs":[{"code":"610322100","name":"城关镇"},{"code":"610322101","name":"虢王镇"},{"code":"610322102","name":"彪角镇"},{"code":"610322103","name":"横水镇"},{"code":"610322104","name":"田家庄镇"},{"code":"610322105","name":"糜杆桥镇"},{"code":"610322107","name":"南指挥镇"},{"code":"610322108","name":"陈村镇"},{"code":"610322109","name":"长青镇"},{"code":"610322110","name":"柳林镇"},{"code":"610322111","name":"姚家沟镇"},{"code":"610322112","name":"范家寨镇"}]},{"code":"610323","name":"岐山县","childs":[{"code":"610323100","name":"凤鸣镇"},{"code":"610323101","name":"蔡家坡镇"},{"code":"610323103","name":"益店镇"},{"code":"610323104","name":"蒲村镇"},{"code":"610323106","name":"青化镇"},{"code":"610323107","name":"枣林镇"},{"code":"610323108","name":"雍川镇"},{"code":"610323111","name":"故郡镇"},{"code":"610323112","name":"京当镇"}]},{"code":"610324","name":"扶风县","childs":[{"code":"610324001","name":"城关街道"},{"code":"610324101","name":"天度镇"},{"code":"610324102","name":"午井镇"},{"code":"610324103","name":"绛帐镇"},{"code":"610324104","name":"段家镇"},{"code":"610324105","name":"杏林镇"},{"code":"610324106","name":"召公镇"},{"code":"610324107","name":"法门镇"}]},{"code":"610326","name":"眉县","childs":[{"code":"610326001","name":"首善街道"},{"code":"610326101","name":"横渠镇"},{"code":"610326102","name":"槐芽镇"},{"code":"610326103","name":"汤峪镇"},{"code":"610326104","name":"常兴镇"},{"code":"610326105","name":"金渠镇"},{"code":"610326106","name":"营头镇"},{"code":"610326107","name":"齐镇"},{"code":"610326400","name":"陕西省太白山旅游区"},{"code":"610326401","name":"红河谷森林公园"}]},{"code":"610327","name":"陇县","childs":[{"code":"610327100","name":"城关镇"},{"code":"610327101","name":"东风镇"},{"code":"610327102","name":"八渡镇"},{"code":"610327104","name":"东南镇"},{"code":"610327106","name":"温水镇"},{"code":"610327107","name":"天成镇"},{"code":"610327108","name":"曹家湾镇"},{"code":"610327109","name":"固关镇"},{"code":"610327112","name":"河北镇"},{"code":"610327113","name":"新集川镇"}]},{"code":"610328","name":"千阳县","childs":[{"code":"610328100","name":"城关镇"},{"code":"610328101","name":"崔家头镇"},{"code":"610328102","name":"南寨镇"},{"code":"610328103","name":"张家塬镇"},{"code":"610328104","name":"水沟镇"},{"code":"610328105","name":"草碧镇"},{"code":"610328107","name":"高崖镇"}]},{"code":"610329","name":"麟游县","childs":[{"code":"610329100","name":"九成宫镇"},{"code":"610329101","name":"崔木镇"},{"code":"610329102","name":"招贤镇"},{"code":"610329103","name":"两亭镇"},{"code":"610329105","name":"常丰镇"},{"code":"610329106","name":"丈八镇"},{"code":"610329107","name":"酒房镇"}]},{"code":"610330","name":"凤县","childs":[{"code":"610330100","name":"双石铺镇"},{"code":"610330101","name":"凤州镇"},{"code":"610330102","name":"黄牛铺镇"},{"code":"610330103","name":"红花铺镇"},{"code":"610330104","name":"河口镇"},{"code":"610330105","name":"唐藏镇"},{"code":"610330106","name":"平木镇"},{"code":"610330107","name":"坪坎镇"},{"code":"610330110","name":"留凤关镇"},{"code":"610330400","name":"马头滩林业局"},{"code":"610330401","name":"辛家山林业场"}]},{"code":"610331","name":"太白县","childs":[{"code":"610331100","name":"咀头镇"},{"code":"610331101","name":"桃川镇"},{"code":"610331102","name":"鹦鸽镇"},{"code":"610331103","name":"靖口镇"},{"code":"610331104","name":"太白河镇"},{"code":"610331105","name":"黄柏塬镇"},{"code":"610331106","name":"王家堎镇"}]}]